gilson_distributions/Binomialdistribution.py
gilson_distributions/Gaussiandistribution.py
gilson_distributions/Generaldistribution.py
gilson_distributions/__init__.py
gilson_distributions-1.0.dist-info/DESCRIPTION.rst
gilson_distributions-1.0.dist-info/METADATA
gilson_distributions-1.0.dist-info/RECORD
gilson_distributions-1.0.dist-info/WHEEL
gilson_distributions-1.0.dist-info/metadata.json
gilson_distributions-1.0.dist-info/top_level.txt
